Metadata-Version: 1.1
Name: sucklesync
Version: 0.3.7
Summary: A wrapper around rsync to simplify continuous sychnronization of remote directories
Home-page: https://github.com/jeremyandrews/sucklesync
Author: Jeremy Andrews
Author-email: jeremy@tag1consulting.com
License: 2-clause BSD
Download-URL: https://github.com/jeremyandrews/sucklesync/archive/v0.3.7-alpha.tar.gz
Platform: UNKNOWN
